[{"x":"241","y":"245","t":[-491,-355],"v":["N","H"]},{"x":"170","y":"246","t":[-491,-353],"v":["N","N"]},{"x":"42","y":"254","t":[-388],"v":["S"]},{"x":"221","y":"246","t":[-353],"v":["A"]},{"x":"171","y":"246","t":[-307],"v":["H"]},{"x":"171","y":"240","t":[-307],"v":["H"]},{"x":"174","y":"253","t":[-307,794],"v":["H","G"]},{"x":"229","y":"246","t":[-142,538,700,799],"v":["S","S","S","H"]},{"x":"12","y":"250","t":[-128],"v":["S"]},{"x":"23","y":"246","t":[-111,787],"v":["S","D"]},{"x":"19","y":"245","t":[-87,279],"v":["S","S"]},{"x":"20","y":"253","t":[-87],"v":["S"]},{"x":"187","y":"247","t":[47],"v":["N"]},{"x":"175","y":"246","t":[78,830],"v":["G","G"]},{"x":"177","y":"247","t":[103],"v":["H"]},{"x":"75","y":"245","t":[221],"v":["N"]},{"x":"69","y":"253","t":[228],"v":["N"]},{"x":"185","y":"250","t":[252],"v":["N"]},{"x":"23","y":"243","t":[284],"v":["S"]},{"x":"19","y":"246","t":[305,787,900,1017],"v":["S","H","S","S"]},{"x":"228","y":"246","t":[520],"v":["S"]},{"x":"21","y":"249","t":[787],"v":["H"]},{"x":"14","y":"252","t":[787],"v":["H"]},{"x":"14","y":"250","t":[787],"v":["D"]},{"x":"22","y":"245","t":[787],"v":["H"]},{"x":"8","y":"249","t":[796],"v":["O"]},{"x":"170","y":"252","t":[942],"v":["S"]},{"x":"176","y":"253","t":[1146],"v":["H"]},{"x":"190","y":"254","t":[1355],"v":["N"]}]