[{"x":"121","y":"160","t":[1990],"v":["?"]},{"x":"114","y":"225","t":[2773],"v":["?"]},{"x":"121","y":"178","t":[5351],"v":["1"]},{"x":"240","y":"202","t":[5970],"v":["?"]},{"x":"227","y":"233","t":[6512],"v":["2"]},{"x":"158","y":"171","t":[12643],"v":["0"]},{"x":"3","y":"150","t":[16947],"v":["0"]},{"x":"194","y":"65","t":[18845],"v":["0"]},{"x":"123","y":"183","t":[19241],"v":["0"]},{"x":"158","y":"150","t":[19241],"v":["2"]},{"x":"167","y":"127","t":[19245],"v":["0"]},{"x":"196","y":"80","t":[20262],"v":["0"]}]