[{"x":"32","y":"249","t":[125],"v":["2"]},{"x":"184","y":"133","t":[163],"v":["3"]},{"x":"246","y":"122","t":[514],"v":["3"]},{"x":"241","y":"39","t":[871],"v":["2"]},{"x":"20","y":"143","t":[881],"v":["2"]},{"x":"175","y":"112","t":[1233],"v":["3"]},{"x":"13","y":"85","t":[1251],"v":["2"]},{"x":"120","y":"94","t":[1251],"v":["2"]},{"x":"84","y":"63","t":[1251],"v":["3"]},{"x":"155","y":"202","t":[1251],"v":["2"]},{"x":"141","y":"110","t":[1251],"v":["1"]},{"x":"84","y":"198","t":[1271],"v":["5"]},{"x":"49","y":"251","t":[1271],"v":["1"]},{"x":"186","y":"206","t":[1271],"v":["1"]},{"x":"99","y":"127","t":[1553],"v":["2"]},{"x":"29","y":"2","t":[1574],"v":["2"]},{"x":"82","y":"96","t":[1618],"v":["4"]},{"x":"149","y":"159","t":[1917],"v":["2"]},{"x":"27","y":"173","t":[1949],"v":["2"]},{"x":"125","y":"32","t":[2338],"v":["1"]},{"x":"61","y":"210","t":[2338],"v":["2"]},{"x":"56","y":"241","t":[2669],"v":["0"]},{"x":"116","y":"69","t":[2703],"v":["?"]},{"x":"14","y":"164","t":[2704],"v":["?"]},{"x":"54","y":"108","t":[2704,15933],"v":["?","1"]},{"x":"197","y":"106","t":[2704],"v":["?"]},{"x":"20","y":"69","t":[2721],"v":["2"]},{"x":"38","y":"106","t":[2739],"v":["1"]},{"x":"177","y":"171","t":[3008],"v":["?"]},{"x":"72","y":"14","t":[3014],"v":["?"]},{"x":"2","y":"61","t":[3099],"v":["0"]},{"x":"93","y":"244","t":[3114],"v":["3"]},{"x":"41","y":"39","t":[3136],"v":["2"]},{"x":"41","y":"232","t":[3408],"v":["1"]},{"x":"64","y":"167","t":[3408],"v":["2"]},{"x":"111","y":"229","t":[3408],"v":["2"]},{"x":"102","y":"219","t":[3408],"v":["2"]},{"x":"117","y":"143","t":[3408],"v":["2"]},{"x":"90","y":"192","t":[3414],"v":["4"]},{"x":"208","y":"39","t":[3414],"v":["2"]},{"x":"190","y":"188","t":[3414],"v":["1"]},{"x":"184","y":"180","t":[3414],"v":["2"]},{"x":"81","y":"255","t":[3422,15908],"v":["2","0"]},{"x":"38","y":"4","t":[3432],"v":["1"]},{"x":"199","y":"124","t":[3435,3463],"v":["2","0"]},{"x":"75","y":"134","t":[3775],"v":["2"]},{"x":"152","y":"171","t":[3775],"v":["1"]},{"x":"229","y":"106","t":[3790],"v":["1"]},{"x":"129","y":"69","t":[3817],"v":["2"]},{"x":"187","y":"206","t":[3817],"v":["2"]},{"x":"38","y":"42","t":[3842],"v":["1"]},{"x":"45","y":"229","t":[3868],"v":["1"]},{"x":"105","y":"216","t":[3880,18398],"v":["1","0"]},{"x":"6","y":"29","t":[3881],"v":["0"]},{"x":"205","y":"42","t":[3890],"v":["1"]},{"x":"227","y":"48","t":[3890],"v":["0"]},{"x":"218","y":"2","t":[3890],"v":["1"]},{"x":"102","y":"216","t":[4125],"v":["1"]},{"x":"246","y":"127","t":[4128,13703],"v":["3","0"]},{"x":"82","y":"12","t":[4230],"v":["0"]},{"x":"238","y":"35","t":[4259],"v":["4"]},{"x":"211","y":"143","t":[4507,5714],"v":["2","2"]},{"x":"157","y":"122","t":[4507],"v":["2"]},{"x":"114","y":"244","t":[4507,9255],"v":["1","0"]},{"x":"14","y":"180","t":[4518],"v":["1"]},{"x":"220","y":"232","t":[4528],"v":["2"]},{"x":"17","y":"35","t":[4820,10125],"v":["2","?"]},{"x":"72","y":"232","t":[4853],"v":["2"]},{"x":"90","y":"213","t":[4853],"v":["2"]},{"x":"184","y":"102","t":[4868,18051],"v":["1","0"]},{"x":"91","y":"73","t":[4874],"v":["0"]},{"x":"102","y":"171","t":[4877],"v":["1"]},{"x":"81","y":"222","t":[5213],"v":["1"]},{"x":"52","y":"204","t":[5221],"v":["3"]},{"x":"172","y":"57","t":[5227],"v":["2"]},{"x":"157","y":"118","t":[5238],"v":["2"]},{"x":"211","y":"94","t":[5238],"v":["1"]},{"x":"97","y":"151","t":[5238],"v":["2"]},{"x":"200","y":"69","t":[5238],"v":["1"]},{"x":"216","y":"39","t":[5254],"v":["0"]},{"x":"167","y":"180","t":[5284],"v":["2"]},{"x":"248","y":"204","t":[5284],"v":["2"]},{"x":"170","y":"110","t":[5299],"v":["2"]},{"x":"54","y":"200","t":[5350],"v":["2"]},{"x":"154","y":"100","t":[5350],"v":["0"]},{"x":"126","y":"18","t":[5352],"v":["4"]},{"x":"129","y":"63","t":[5352],"v":["2"]},{"x":"105","y":"94","t":[5601],"v":["4"]},{"x":"91","y":"84","t":[5611],"v":["2"]},{"x":"56","y":"81","t":[5611],"v":["2"]},{"x":"132","y":"35","t":[5611],"v":["2"]},{"x":"172","y":"206","t":[5620],"v":["1"]},{"x":"54","y":"204","t":[5621],"v":["2"]},{"x":"84","y":"29","t":[5629,12574,18546],"v":["?","2","1"]},{"x":"205","y":"124","t":[5661],"v":["?"]},{"x":"41","y":"127","t":[5726],"v":["2"]},{"x":"184","y":"116","t":[5735],"v":["2"]},{"x":"168","y":"247","t":[5739],"v":["2"]},{"x":"123","y":"167","t":[5978],"v":["2"]},{"x":"188","y":"183","t":[6003],"v":["2"]},{"x":"241","y":"151","t":[6003],"v":["1"]},{"x":"159","y":"121","t":[6003],"v":["2"]},{"x":"202","y":"106","t":[6003],"v":["1"]},{"x":"138","y":"186","t":[6048,12176],"v":["?","1"]},{"x":"5","y":"39","t":[6050],"v":["?"]},{"x":"67","y":"24","t":[6050],"v":["?"]},{"x":"179","y":"32","t":[6128],"v":["5"]},{"x":"229","y":"188","t":[6128],"v":["3"]},{"x":"166","y":"180","t":[6128],"v":["2"]},{"x":"245","y":"84","t":[6128],"v":["2"]},{"x":"164","y":"73","t":[6129],"v":["?"]},{"x":"145","y":"57","t":[6326],"v":["2"]},{"x":"173","y":"73","t":[6364],"v":["?"]},{"x":"182","y":"124","t":[6364],"v":["2"]},{"x":"177","y":"146","t":[6365],"v":["1"]},{"x":"184","y":"130","t":[6365],"v":["2"]},{"x":"131","y":"67","t":[6365],"v":["4"]},{"x":"113","y":"85","t":[6365],"v":["2"]},{"x":"167","y":"247","t":[6366],"v":["2"]},{"x":"209","y":"249","t":[6366],"v":["2"]},{"x":"159","y":"118","t":[6373],"v":["1"]},{"x":"187","y":"176","t":[6417],"v":["?"]},{"x":"222","y":"167","t":[6661],"v":["0"]},{"x":"231","y":"183","t":[6665],"v":["2"]},{"x":"228","y":"36","t":[6707],"v":["5"]},{"x":"63","y":"165","t":[6707,18030],"v":["1","0"]},{"x":"184","y":"26","t":[6747,18051],"v":["1","0"]},{"x":"17","y":"204","t":[7092],"v":["?"]},{"x":"245","y":"124","t":[7094],"v":["1"]},{"x":"184","y":"204","t":[7110],"v":["?"]},{"x":"187","y":"208","t":[7110],"v":["?"]},{"x":"229","y":"124","t":[7110],"v":["0"]},{"x":"207","y":"57","t":[7114],"v":["1"]},{"x":"38","y":"130","t":[7116],"v":["2"]},{"x":"158","y":"122","t":[7117,9983],"v":["2","?"]},{"x":"184","y":"122","t":[7117],"v":["1"]},{"x":"105","y":"112","t":[7134],"v":["1"]},{"x":"232","y":"104","t":[7134],"v":["?"]},{"x":"193","y":"189","t":[7134],"v":["?"]},{"x":"2","y":"90","t":[7144],"v":["3"]},{"x":"27","y":"116","t":[7144],"v":["2"]},{"x":"38","y":"55","t":[7157],"v":["2"]},{"x":"108","y":"121","t":[7206],"v":["1"]},{"x":"184","y":"128","t":[7432],"v":["?"]},{"x":"254","y":"232","t":[7434],"v":["1"]},{"x":"35","y":"195","t":[7434],"v":["2"]},{"x":"197","y":"128","t":[7434,8525],"v":["1","0"]},{"x":"208","y":"112","t":[7434],"v":["1"]},{"x":"102","y":"189","t":[7444],"v":["?"]},{"x":"199","y":"91","t":[7497],"v":["2"]},{"x":"76","y":"247","t":[7793],"v":["1"]},{"x":"229","y":"213","t":[7805],"v":["1"]},{"x":"236","y":"63","t":[7818],"v":["2"]},{"x":"52","y":"118","t":[7824],"v":["1"]},{"x":"13","y":"4","t":[7941],"v":["3"]},{"x":"238","y":"226","t":[8189],"v":["2"]},{"x":"58","y":"112","t":[8191],"v":["2"]},{"x":"68","y":"122","t":[8191],"v":["2"]},{"x":"143","y":"238","t":[8197],"v":["2"]},{"x":"40","y":"183","t":[8286],"v":["1"]},{"x":"105","y":"247","t":[8288],"v":["0"]},{"x":"131","y":"232","t":[8288],"v":["1"]},{"x":"147","y":"30","t":[8288],"v":["1"]},{"x":"29","y":"106","t":[8507],"v":["1"]},{"x":"116","y":"247","t":[8507],"v":["1"]},{"x":"163","y":"241","t":[8507],"v":["2"]},{"x":"234","y":"167","t":[8553],"v":["2"]},{"x":"154","y":"243","t":[8565],"v":["0"]},{"x":"182","y":"133","t":[8580],"v":["1"]},{"x":"126","y":"66","t":[8662],"v":["3"]},{"x":"231","y":"100","t":[8662],"v":["1"]},{"x":"26","y":"186","t":[8666],"v":["2"]},{"x":"166","y":"30","t":[8667],"v":["2"]},{"x":"186","y":"5","t":[8667],"v":["2"]},{"x":"195","y":"12","t":[8667],"v":["2"]},{"x":"196","y":"173","t":[8881],"v":["0"]},{"x":"50","y":"237","t":[8896],"v":["3"]},{"x":"147","y":"41","t":[8913],"v":["0"]},{"x":"220","y":"36","t":[8917],"v":["0"]},{"x":"136","y":"42","t":[8923],"v":["1"]},{"x":"123","y":"69","t":[8932],"v":["1"]},{"x":"250","y":"118","t":[8932],"v":["0"]},{"x":"177","y":"137","t":[8932,15053],"v":["2","0"]},{"x":"182","y":"164","t":[8932,12000,14679],"v":["4","0","2"]},{"x":"179","y":"94","t":[8936],"v":["2"]},{"x":"70","y":"118","t":[8947],"v":["0"]},{"x":"11","y":"153","t":[9255],"v":["2"]},{"x":"36","y":"173","t":[9255],"v":["2"]},{"x":"167","y":"249","t":[9255,11478],"v":["2","1"]},{"x":"43","y":"4","t":[9283],"v":["2"]},{"x":"157","y":"189","t":[9293],"v":["1"]},{"x":"193","y":"208","t":[9297],"v":["2"]},{"x":"84","y":"8","t":[9300],"v":["0"]},{"x":"146","y":"159","t":[9598],"v":["2"]},{"x":"214","y":"216","t":[9607],"v":["1"]},{"x":"154","y":"195","t":[9657],"v":["1"]},{"x":"145","y":"204","t":[9657],"v":["1"]},{"x":"138","y":"165","t":[9658,18423],"v":["3","0"]},{"x":"159","y":"139","t":[9658],"v":["5"]},{"x":"166","y":"127","t":[9658],"v":["2"]},{"x":"172","y":"121","t":[9658],"v":["3"]},{"x":"179","y":"116","t":[9658],"v":["2"]},{"x":"45","y":"202","t":[9658],"v":["2"]},{"x":"2","y":"198","t":[9671],"v":["4"]},{"x":"207","y":"189","t":[9703],"v":["2"]},{"x":"81","y":"122","t":[9717],"v":["2"]},{"x":"127","y":"73","t":[9983],"v":["2"]},{"x":"68","y":"63","t":[9983],"v":["?"]},{"x":"134","y":"66","t":[9983],"v":["4"]},{"x":"99","y":"157","t":[9983],"v":["?"]},{"x":"96","y":"149","t":[9983,13326],"v":["?","2"]},{"x":"72","y":"91","t":[9997],"v":["?"]},{"x":"184","y":"164","t":[10086],"v":["?"]},{"x":"63","y":"155","t":[10125],"v":["?"]},{"x":"159","y":"48","t":[10390],"v":["?"]},{"x":"97","y":"100","t":[10400],"v":["?"]},{"x":"35","y":"24","t":[10410],"v":["?"]},{"x":"35","y":"91","t":[10410],"v":["?"]},{"x":"222","y":"134","t":[10483],"v":["3"]},{"x":"54","y":"206","t":[10666],"v":["1"]},{"x":"193","y":"200","t":[10677],"v":["2"]},{"x":"84","y":"20","t":[10768],"v":["0"]},{"x":"93","y":"53","t":[10768,14759],"v":["4","1"]},{"x":"125","y":"12","t":[10768],"v":["1"]},{"x":"141","y":"18","t":[10768],"v":["1"]},{"x":"166","y":"67","t":[10768],"v":["2"]},{"x":"172","y":"79","t":[10768],"v":["2"]},{"x":"129","y":"171","t":[10768],"v":["1"]},{"x":"157","y":"180","t":[10780],"v":["0"]},{"x":"182","y":"29","t":[10783],"v":["1"]},{"x":"55","y":"204","t":[10797],"v":["1"]},{"x":"173","y":"157","t":[10800],"v":["0"]},{"x":"159","y":"79","t":[10820],"v":["1"]},{"x":"243","y":"164","t":[10827],"v":["1"]},{"x":"187","y":"112","t":[10829],"v":["0"]},{"x":"59","y":"57","t":[11104],"v":["1"]},{"x":"99","y":"67","t":[11104],"v":["1"]},{"x":"164","y":"85","t":[11104,15534],"v":["1","0"]},{"x":"63","y":"116","t":[11104],"v":["1"]},{"x":"179","y":"180","t":[11112],"v":["1"]},{"x":"147","y":"36","t":[11119],"v":["1"]},{"x":"172","y":"222","t":[11120],"v":["1"]},{"x":"63","y":"208","t":[11140],"v":["1"]},{"x":"72","y":"29","t":[11155],"v":["2"]},{"x":"0","y":"5","t":[11155],"v":["2"]},{"x":"136","y":"18","t":[11218],"v":["2"]},{"x":"172","y":"110","t":[11244],"v":["1"]},{"x":"54","y":"192","t":[11408],"v":["1"]},{"x":"132","y":"137","t":[11413],"v":["0"]},{"x":"188","y":"192","t":[11420],"v":["0"]},{"x":"223","y":"145","t":[11420],"v":["2"]},{"x":"205","y":"195","t":[11420,14005],"v":["0","1"]},{"x":"56","y":"237","t":[11463],"v":["0"]},{"x":"88","y":"200","t":[11463],"v":["0"]},{"x":"82","y":"198","t":[11463],"v":["0"]},{"x":"102","y":"202","t":[11463],"v":["0"]},{"x":"120","y":"202","t":[11463],"v":["0"]},{"x":"126","y":"198","t":[11463],"v":["0"]},{"x":"140","y":"202","t":[11463],"v":["1"]},{"x":"127","y":"29","t":[11483],"v":["2"]},{"x":"81","y":"249","t":[11485],"v":["0"]},{"x":"86","y":"63","t":[11494,13355],"v":["1","2"]},{"x":"132","y":"198","t":[11777],"v":["1"]},{"x":"109","y":"51","t":[11809],"v":["1"]},{"x":"214","y":"206","t":[11820,19118],"v":["1","0"]},{"x":"4","y":"194","t":[11820],"v":["0"]},{"x":"113","y":"97","t":[11822],"v":["1"]},{"x":"113","y":"96","t":[11822],"v":["1"]},{"x":"149","y":"206","t":[11825],"v":["0"]},{"x":"73","y":"57","t":[11831],"v":["0"]},{"x":"195","y":"238","t":[11844],"v":["0"]},{"x":"182","y":"180","t":[11851,12578,17992],"v":["1","0","0"]},{"x":"131","y":"219","t":[11851],"v":["1"]},{"x":"136","y":"151","t":[11853],"v":["0"]},{"x":"150","y":"130","t":[11883],"v":["1"]},{"x":"68","y":"176","t":[12171],"v":["1"]},{"x":"182","y":"171","t":[12176],"v":["1"]},{"x":"190","y":"182","t":[12176],"v":["2"]},{"x":"67","y":"134","t":[12197],"v":["1"]},{"x":"97","y":"170","t":[12197],"v":["1"]},{"x":"173","y":"159","t":[12233,12668],"v":["0","1"]},{"x":"106","y":"244","t":[12234],"v":["0"]},{"x":"64","y":"91","t":[12532],"v":["2"]},{"x":"100","y":"124","t":[12532],"v":["0"]},{"x":"4","y":"79","t":[12574],"v":["2"]},{"x":"50","y":"232","t":[12574],"v":["2"]},{"x":"22","y":"91","t":[12574],"v":["2"]},{"x":"38","y":"51","t":[12574],"v":["2"]},{"x":"70","y":"26","t":[12574],"v":["2"]},{"x":"136","y":"29","t":[12574],"v":["2"]},{"x":"200","y":"251","t":[12574],"v":["1"]},{"x":"118","y":"202","t":[12578],"v":["0"]},{"x":"173","y":"182","t":[12578],"v":["0"]},{"x":"182","y":"177","t":[12578],"v":["0"]},{"x":"202","y":"145","t":[12579],"v":["0"]},{"x":"150","y":"41","t":[12583],"v":["1"]},{"x":"222","y":"10","t":[12583,12589],"v":["1","1"]},{"x":"0","y":"189","t":[12584],"v":["0"]},{"x":"72","y":"171","t":[12588],"v":["0"]},{"x":"182","y":"127","t":[12589,16184,18030,20337,20402],"v":["0","1","0","1","0"]},{"x":"22","y":"220","t":[12593],"v":["0"]},{"x":"250","y":"237","t":[12703],"v":["1"]},{"x":"199","y":"189","t":[12912],"v":["0"]},{"x":"249","y":"220","t":[12912],"v":["1"]},{"x":"86","y":"41","t":[12924],"v":["0"]},{"x":"43","y":"2","t":[12931],"v":["0"]},{"x":"105","y":"251","t":[12948],"v":["0"]},{"x":"43","y":"219","t":[12955],"v":["0"]},{"x":"43","y":"226","t":[12955],"v":["0"]},{"x":"41","y":"225","t":[12955],"v":["1"]},{"x":"114","y":"243","t":[12958],"v":["0"]},{"x":"109","y":"235","t":[12958],"v":["0"]},{"x":"136","y":"177","t":[12958],"v":["0"]},{"x":"43","y":"75","t":[13006],"v":["1"]},{"x":"100","y":"39","t":[13006],"v":["1"]},{"x":"88","y":"202","t":[13223],"v":["1"]},{"x":"17","y":"128","t":[13262,18030],"v":["0","1"]},{"x":"255","y":"253","t":[13274],"v":["0"]},{"x":"199","y":"176","t":[13274],"v":["0"]},{"x":"237","y":"182","t":[13274],"v":["1"]},{"x":"163","y":"180","t":[13275],"v":["0"]},{"x":"161","y":"182","t":[13275],"v":["0"]},{"x":"163","y":"183","t":[13275],"v":["0"]},{"x":"163","y":"177","t":[13275],"v":["0"]},{"x":"158","y":"177","t":[13275],"v":["0"]},{"x":"155","y":"149","t":[13275],"v":["0"]},{"x":"166","y":"170","t":[13275],"v":["0"]},{"x":"214","y":"255","t":[13307],"v":["0"]},{"x":"245","y":"214","t":[13307],"v":["0"]},{"x":"99","y":"189","t":[13326,15053],"v":["2","0"]},{"x":"172","y":"182","t":[13326],"v":["2"]},{"x":"164","y":"251","t":[13340],"v":["2"]},{"x":"31","y":"4","t":[13355],"v":["1"]},{"x":"2","y":"122","t":[13355,15883,18777],"v":["0","0","0"]},{"x":"231","y":"195","t":[13372],"v":["1"]},{"x":"184","y":"161","t":[13417],"v":["4"]},{"x":"126","y":"73","t":[13417],"v":["0"]},{"x":"182","y":"149","t":[13633],"v":["0"]},{"x":"56","y":"247","t":[13651],"v":["1"]},{"x":"2","y":"222","t":[13657],"v":["1"]},{"x":"0","y":"198","t":[13657],"v":["1"]},{"x":"45","y":"255","t":[13657],"v":["0"]},{"x":"26","y":"214","t":[13657],"v":["1"]},{"x":"38","y":"194","t":[13662],"v":["1"]},{"x":"145","y":"164","t":[13662],"v":["0"]},{"x":"116","y":"244","t":[13686],"v":["0"]},{"x":"241","y":"200","t":[13700],"v":["0"]},{"x":"15","y":"30","t":[13700],"v":["0"]},{"x":"193","y":"94","t":[13700],"v":["1"]},{"x":"111","y":"96","t":[13740,17679],"v":["0","0"]},{"x":"2","y":"124","t":[14004],"v":["0"]},{"x":"77","y":"170","t":[14073],"v":["0"]},{"x":"86","y":"222","t":[14073,18398],"v":["1","0"]},{"x":"131","y":"69","t":[14111],"v":["1"]},{"x":"9","y":"255","t":[14111],"v":["0"]},{"x":"72","y":"238","t":[14111],"v":["1"]},{"x":"117","y":"24","t":[14354],"v":["0"]},{"x":"138","y":"97","t":[14354],"v":["0"]},{"x":"155","y":"108","t":[14358],"v":["1"]},{"x":"13","y":"170","t":[14359],"v":["0"]},{"x":"22","y":"177","t":[14359],"v":["0"]},{"x":"47","y":"96","t":[14359],"v":["1"]},{"x":"82","y":"255","t":[14386],"v":["4"]},{"x":"164","y":"102","t":[14386],"v":["4"]},{"x":"255","y":"128","t":[14386],"v":["0"]},{"x":"217","y":"53","t":[14387],"v":["0"]},{"x":"223","y":"96","t":[14392],"v":["4"]},{"x":"159","y":"69","t":[14440,19969],"v":["1","0"]},{"x":"11","y":"157","t":[14492],"v":["0"]},{"x":"15","y":"170","t":[14492],"v":["1"]},{"x":"152","y":"177","t":[14679],"v":["0"]},{"x":"145","y":"127","t":[14679],"v":["2"]},{"x":"161","y":"108","t":[14679],"v":["1"]},{"x":"204","y":"128","t":[14679],"v":["3"]},{"x":"72","y":"198","t":[14770],"v":["1"]},{"x":"76","y":"222","t":[14770],"v":["0"]},{"x":"193","y":"53","t":[14770],"v":["0"]},{"x":"218","y":"189","t":[14771],"v":["0"]},{"x":"173","y":"176","t":[14774],"v":["0"]},{"x":"223","y":"189","t":[14774],"v":["0"]},{"x":"25","y":"48","t":[14774],"v":["1"]},{"x":"32","y":"214","t":[14774],"v":["0"]},{"x":"99","y":"32","t":[14777],"v":["2"]},{"x":"154","y":"97","t":[14777,15109],"v":["1","0"]},{"x":"223","y":"53","t":[14786],"v":["3"]},{"x":"228","y":"69","t":[14786],"v":["0"]},{"x":"157","y":"48","t":[14787],"v":["0"]},{"x":"164","y":"41","t":[14787],"v":["1"]},{"x":"184","y":"97","t":[14799],"v":["0"]},{"x":"232","y":"102","t":[14799],"v":["0"]},{"x":"147","y":"55","t":[14813],"v":["0"]},{"x":"27","y":"145","t":[14843],"v":["1"]},{"x":"138","y":"134","t":[15053],"v":["2"]},{"x":"181","y":"143","t":[15053],"v":["3"]},{"x":"238","y":"97","t":[15053],"v":["2"]},{"x":"202","y":"78","t":[15053],"v":["1"]},{"x":"18","y":"164","t":[15088],"v":["1"]},{"x":"25","y":"128","t":[15088,17664],"v":["3","0"]},{"x":"14","y":"208","t":[15091],"v":["0"]},{"x":"207","y":"97","t":[15091],"v":["1"]},{"x":"108","y":"48","t":[15091],"v":["1"]},{"x":"79","y":"32","t":[15091,17677],"v":["1","0"]},{"x":"70","y":"29","t":[15091],"v":["1"]},{"x":"175","y":"72","t":[15109],"v":["2"]},{"x":"175","y":"42","t":[15109],"v":["0"]},{"x":"232","y":"61","t":[15137],"v":["1"]},{"x":"25","y":"90","t":[15191],"v":["0"]},{"x":"238","y":"110","t":[15227],"v":["1"]},{"x":"145","y":"143","t":[15403],"v":["0"]},{"x":"96","y":"45","t":[15443],"v":["1"]},{"x":"195","y":"18","t":[15474,15894],"v":["0","0"]},{"x":"14","y":"90","t":[15505],"v":["0"]},{"x":"25","y":"210","t":[15505],"v":["2"]},{"x":"26","y":"173","t":[15505],"v":["0"]},{"x":"229","y":"94","t":[15512],"v":["0"]},{"x":"227","y":"45","t":[15532],"v":["1"]},{"x":"54","y":"220","t":[15534],"v":["0"]},{"x":"114","y":"238","t":[15534],"v":["1"]},{"x":"150","y":"115","t":[15862,17679],"v":["0","0"]},{"x":"45","y":"241","t":[15867],"v":["1"]},{"x":"170","y":"48","t":[15870],"v":["0"]},{"x":"82","y":"41","t":[15883],"v":["0"]},{"x":"79","y":"29","t":[15883],"v":["2"]},{"x":"97","y":"97","t":[15883],"v":["0"]},{"x":"123","y":"124","t":[15883],"v":["0"]},{"x":"96","y":"127","t":[15883],"v":["0"]},{"x":"152","y":"133","t":[15883],"v":["1"]},{"x":"116","y":"206","t":[15883],"v":["0"]},{"x":"56","y":"165","t":[15892],"v":["0"]},{"x":"102","y":"128","t":[15892],"v":["0"]},{"x":"34","y":"133","t":[15892],"v":["0"]},{"x":"158","y":"121","t":[15892],"v":["0"]},{"x":"146","y":"149","t":[15892],"v":["1"]},{"x":"6","y":"173","t":[15892],"v":["1"]},{"x":"255","y":"249","t":[15893],"v":["0"]},{"x":"246","y":"124","t":[15902],"v":["0"]},{"x":"231","y":"180","t":[15902],"v":["0"]},{"x":"18","y":"229","t":[15937],"v":["0"]},{"x":"84","y":"220","t":[16172],"v":["3"]},{"x":"229","y":"122","t":[16172],"v":["1"]},{"x":"17","y":"69","t":[16224],"v":["1"]},{"x":"47","y":"57","t":[16224],"v":["1"]},{"x":"164","y":"84","t":[16225],"v":["0"]},{"x":"158","y":"112","t":[16225],"v":["0"]},{"x":"182","y":"26","t":[16237],"v":["0"]},{"x":"150","y":"10","t":[16237],"v":["0"]},{"x":"140","y":"14","t":[16237],"v":["0"]},{"x":"143","y":"30","t":[16237],"v":["0"]},{"x":"193","y":"110","t":[16238],"v":["1"]},{"x":"34","y":"149","t":[16347],"v":["1"]},{"x":"65","y":"122","t":[16580],"v":["4"]},{"x":"109","y":"244","t":[16580,20540],"v":["4","0"]},{"x":"88","y":"157","t":[16580],"v":["4"]},{"x":"43","y":"124","t":[16580],"v":["1"]},{"x":"73","y":"146","t":[16580],"v":["2"]},{"x":"122","y":"79","t":[16580],"v":["1"]},{"x":"177","y":"116","t":[16589],"v":["0"]},{"x":"216","y":"67","t":[16590],"v":["0"]},{"x":"252","y":"249","t":[16928],"v":["0"]},{"x":"84","y":"146","t":[16996,17716],"v":["0","0"]},{"x":"15","y":"192","t":[17004],"v":["1"]},{"x":"114","y":"140","t":[17009],"v":["0"]},{"x":"196","y":"167","t":[17296],"v":["0"]},{"x":"225","y":"153","t":[17296],"v":["0"]},{"x":"204","y":"195","t":[17296,18398],"v":["0","1"]},{"x":"241","y":"41","t":[17320],"v":["1"]},{"x":"152","y":"8","t":[17330],"v":["1"]},{"x":"6","y":"39","t":[17372],"v":["0"]},{"x":"154","y":"146","t":[17390],"v":["0"]},{"x":"182","y":"231","t":[17392],"v":["0"]},{"x":"187","y":"213","t":[17392],"v":["0"]},{"x":"104","y":"104","t":[17625],"v":["0"]},{"x":"141","y":"100","t":[17625],"v":["0"]},{"x":"97","y":"122","t":[17625],"v":["0"]},{"x":"126","y":"5","t":[17664],"v":["2"]},{"x":"158","y":"48","t":[17664],"v":["1"]},{"x":"26","y":"130","t":[17664],"v":["1"]},{"x":"67","y":"100","t":[17664],"v":["0"]},{"x":"191","y":"189","t":[17668],"v":["0"]},{"x":"213","y":"206","t":[17668],"v":["0"]},{"x":"77","y":"195","t":[17670],"v":["1"]},{"x":"55","y":"35","t":[17677],"v":["0"]},{"x":"59","y":"26","t":[17677],"v":["0"]},{"x":"88","y":"97","t":[17677],"v":["0"]},{"x":"2","y":"121","t":[17677],"v":["0"]},{"x":"49","y":"122","t":[17677],"v":["0"]},{"x":"159","y":"124","t":[17679],"v":["0"]},{"x":"191","y":"134","t":[17679],"v":["1"]},{"x":"170","y":"206","t":[17698],"v":["1"]},{"x":"75","y":"72","t":[17703],"v":["0"]},{"x":"199","y":"10","t":[17707],"v":["2"]},{"x":"208","y":"10","t":[17707],"v":["2"]},{"x":"245","y":"59","t":[17707],"v":["2"]},{"x":"11","y":"140","t":[17709],"v":["2"]},{"x":"140","y":"140","t":[17709],"v":["2"]},{"x":"143","y":"186","t":[17709],"v":["1"]},{"x":"248","y":"124","t":[17709],"v":["1"]},{"x":"177","y":"194","t":[17709],"v":["0"]},{"x":"177","y":"198","t":[17709],"v":["0"]},{"x":"238","y":"157","t":[17719],"v":["0"]},{"x":"170","y":"231","t":[17989,17992],"v":["0","2"]},{"x":"177","y":"145","t":[17992],"v":["1"]},{"x":"34","y":"255","t":[17992],"v":["1"]},{"x":"118","y":"249","t":[17992],"v":["4"]},{"x":"191","y":"244","t":[17992],"v":["3"]},{"x":"2","y":"112","t":[18030],"v":["0"]},{"x":"2","y":"115","t":[18030],"v":["0"]},{"x":"4","y":"229","t":[18030],"v":["2"]},{"x":"134","y":"151","t":[18030],"v":["0"]},{"x":"67","y":"96","t":[18041],"v":["0"]},{"x":"95","y":"81","t":[18046],"v":["0"]},{"x":"134","y":"84","t":[18051],"v":["1"]},{"x":"172","y":"59","t":[18051],"v":["0"]},{"x":"195","y":"53","t":[18051],"v":["1"]},{"x":"168","y":"85","t":[18051],"v":["0"]},{"x":"179","y":"112","t":[18051],"v":["1"]},{"x":"145","y":"32","t":[18053],"v":["0"]},{"x":"155","y":"26","t":[18053],"v":["0"]},{"x":"170","y":"18","t":[18053],"v":["0"]},{"x":"61","y":"171","t":[18077],"v":["1"]},{"x":"249","y":"61","t":[18077],"v":["2"]},{"x":"91","y":"213","t":[18398],"v":["0"]},{"x":"77","y":"200","t":[18398],"v":["0"]},{"x":"205","y":"189","t":[18398],"v":["0"]},{"x":"214","y":"84","t":[18402],"v":["0"]},{"x":"136","y":"145","t":[18410],"v":["0"]},{"x":"154","y":"151","t":[18410],"v":["0"]},{"x":"158","y":"159","t":[18410],"v":["0"]},{"x":"190","y":"171","t":[18410],"v":["1"]},{"x":"193","y":"170","t":[18410],"v":["0"]},{"x":"125","y":"164","t":[18423],"v":["0"]},{"x":"216","y":"121","t":[18424],"v":["1"]},{"x":"172","y":"214","t":[18436],"v":["0"]},{"x":"155","y":"121","t":[18467],"v":["0"]},{"x":"108","y":"145","t":[18467],"v":["1"]},{"x":"38","y":"200","t":[18467],"v":["0"]},{"x":"75","y":"8","t":[18516],"v":["0"]},{"x":"157","y":"177","t":[18723],"v":["0"]},{"x":"81","y":"237","t":[18723],"v":["1"]},{"x":"17","y":"255","t":[18726],"v":["0"]},{"x":"14","y":"220","t":[18726],"v":["1"]},{"x":"13","y":"177","t":[18726],"v":["0"]},{"x":"181","y":"170","t":[18726],"v":["0"]},{"x":"99","y":"153","t":[18726],"v":["1"]},{"x":"113","y":"128","t":[18726],"v":["0"]},{"x":"146","y":"124","t":[18726],"v":["0"]},{"x":"123","y":"112","t":[18726],"v":["0"]},{"x":"145","y":"122","t":[18726],"v":["1"]},{"x":"145","y":"112","t":[18726],"v":["1"]},{"x":"147","y":"97","t":[18726,19883],"v":["0","0"]},{"x":"164","y":"78","t":[18726],"v":["1"]},{"x":"216","y":"171","t":[18726],"v":["1"]},{"x":"190","y":"67","t":[18735],"v":["1"]},{"x":"123","y":"130","t":[18755],"v":["0"]},{"x":"246","y":"100","t":[18755],"v":["1"]},{"x":"255","y":"96","t":[18755],"v":["2"]},{"x":"173","y":"139","t":[18755],"v":["0"]},{"x":"168","y":"145","t":[18755],"v":["1"]},{"x":"22","y":"127","t":[18777],"v":["0"]},{"x":"26","y":"145","t":[18777],"v":["0"]},{"x":"6","y":"17","t":[18789,21344],"v":["1","1"]},{"x":"81","y":"124","t":[18794],"v":["0"]},{"x":"173","y":"189","t":[18830],"v":["0"]},{"x":"20","y":"140","t":[18854],"v":["1"]},{"x":"157","y":"226","t":[18874],"v":["0"]},{"x":"170","y":"186","t":[18874],"v":["1"]},{"x":"202","y":"237","t":[18888],"v":["0"]},{"x":"86","y":"143","t":[19097],"v":["0"]},{"x":"158","y":"145","t":[19097],"v":["0"]},{"x":"225","y":"97","t":[19098],"v":["0"]},{"x":"196","y":"171","t":[19098],"v":["0"]},{"x":"193","y":"164","t":[19098],"v":["1"]},{"x":"227","y":"14","t":[19162],"v":["1"]},{"x":"228","y":"231","t":[19485],"v":["1"]},{"x":"175","y":"85","t":[19545],"v":["0"]},{"x":"164","y":"2","t":[19550],"v":["0"]},{"x":"143","y":"53","t":[19556],"v":["0"]},{"x":"114","y":"249","t":[19609],"v":["0"]},{"x":"32","y":"188","t":[19849],"v":["1"]},{"x":"54","y":"216","t":[19849],"v":["1"]},{"x":"254","y":"81","t":[19862],"v":["0"]},{"x":"241","y":"85","t":[19862],"v":["0"]},{"x":"254","y":"79","t":[19862],"v":["0"]},{"x":"32","y":"2","t":[19862],"v":["1"]},{"x":"93","y":"30","t":[19862],"v":["1"]},{"x":"100","y":"30","t":[19862],"v":["2"]},{"x":"164","y":"32","t":[19862],"v":["0"]},{"x":"105","y":"200","t":[19863],"v":["1"]},{"x":"126","y":"192","t":[19863],"v":["0"]},{"x":"200","y":"145","t":[19863],"v":["0"]},{"x":"134","y":"189","t":[19863],"v":["0"]},{"x":"138","y":"177","t":[19863],"v":["1"]},{"x":"236","y":"165","t":[19863],"v":["0"]},{"x":"147","y":"177","t":[19863],"v":["0"]},{"x":"246","y":"140","t":[19863],"v":["0"]},{"x":"234","y":"164","t":[19863],"v":["0"]},{"x":"246","y":"155","t":[19863],"v":["0"]},{"x":"147","y":"167","t":[19863],"v":["0"]},{"x":"240","y":"153","t":[19863],"v":["0"]},{"x":"225","y":"151","t":[19863],"v":["0"]},{"x":"229","y":"139","t":[19863],"v":["1"]},{"x":"26","y":"182","t":[19863],"v":["0"]},{"x":"179","y":"153","t":[19863],"v":["0"]},{"x":"88","y":"192","t":[19863],"v":["0"]},{"x":"166","y":"210","t":[19863,19865],"v":["1","0"]},{"x":"136","y":"202","t":[19865],"v":["0"]},{"x":"54","y":"20","t":[19883],"v":["3"]},{"x":"59","y":"12","t":[19883],"v":["1"]},{"x":"100","y":"69","t":[19883],"v":["0"]},{"x":"108","y":"84","t":[19883],"v":["0"]},{"x":"117","y":"78","t":[19883],"v":["0"]},{"x":"118","y":"78","t":[19883],"v":["0"]},{"x":"131","y":"84","t":[19883],"v":["0"]},{"x":"140","y":"90","t":[19883],"v":["0"]},{"x":"140","y":"85","t":[19883],"v":["0"]},{"x":"152","y":"110","t":[19883],"v":["0"]},{"x":"158","y":"116","t":[19883],"v":["0"]},{"x":"90","y":"75","t":[19907],"v":["0"]},{"x":"200","y":"104","t":[19936],"v":["0"]},{"x":"213","y":"108","t":[19936],"v":["1"]},{"x":"238","y":"116","t":[19936],"v":["1"]},{"x":"116","y":"100","t":[19941],"v":["0"]},{"x":"228","y":"66","t":[19949],"v":["0"]},{"x":"231","y":"63","t":[19949],"v":["1"]},{"x":"127","y":"39","t":[19959],"v":["0"]},{"x":"199","y":"145","t":[19959],"v":["0"]},{"x":"199","y":"143","t":[19959],"v":["0"]},{"x":"229","y":"140","t":[19959],"v":["1"]},{"x":"113","y":"143","t":[19969],"v":["1"]},{"x":"109","y":"128","t":[19969],"v":["0"]},{"x":"170","y":"200","t":[19969],"v":["0"]},{"x":"190","y":"243","t":[19969],"v":["0"]},{"x":"204","y":"157","t":[19969],"v":["0"]},{"x":"213","y":"145","t":[19969],"v":["1"]},{"x":"220","y":"133","t":[19969],"v":["0"]},{"x":"143","y":"81","t":[20175],"v":["0"]},{"x":"150","y":"73","t":[20175],"v":["0"]},{"x":"170","y":"67","t":[20175],"v":["0"]},{"x":"191","y":"48","t":[20175],"v":["1"]},{"x":"50","y":"182","t":[20216],"v":["0"]},{"x":"49","y":"182","t":[20216],"v":["0"]},{"x":"64","y":"170","t":[20216],"v":["0"]},{"x":"109","y":"91","t":[20224],"v":["1"]},{"x":"181","y":"66","t":[20224],"v":["0"]},{"x":"216","y":"226","t":[20250],"v":["0"]},{"x":"218","y":"225","t":[20250],"v":["0"]},{"x":"238","y":"206","t":[20250],"v":["0"]},{"x":"36","y":"110","t":[20291],"v":["0"]},{"x":"122","y":"10","t":[20292],"v":["0"]},{"x":"97","y":"140","t":[20402],"v":["1"]},{"x":"143","y":"160","t":[20402],"v":["2"]},{"x":"140","y":"110","t":[20402],"v":["3"]},{"x":"155","y":"139","t":[20402],"v":["1"]},{"x":"175","y":"128","t":[20402],"v":["2"]},{"x":"182","y":"110","t":[20402],"v":["0"]},{"x":"191","y":"110","t":[20402],"v":["1"]},{"x":"188","y":"78","t":[20402],"v":["0"]},{"x":"229","y":"73","t":[20402],"v":["0"]},{"x":"106","y":"251","t":[20540],"v":["0"]},{"x":"146","y":"186","t":[20540],"v":["0"]},{"x":"197","y":"194","t":[20543],"v":["0"]},{"x":"205","y":"186","t":[20543],"v":["0"]},{"x":"59","y":"167","t":[20556],"v":["0"]},{"x":"86","y":"91","t":[20673],"v":["0"]},{"x":"200","y":"45","t":[20696],"v":["0"]},{"x":"193","y":"47","t":[20696],"v":["0"]},{"x":"208","y":"20","t":[20696],"v":["0"]},{"x":"27","y":"247","t":[20941],"v":["2"]},{"x":"21","y":"215","t":[20941],"v":["1"]},{"x":"58","y":"231","t":[20942],"v":["2"]},{"x":"96","y":"154","t":[20942],"v":["1"]},{"x":"139","y":"246","t":[20942],"v":["0"]},{"x":"182","y":"91","t":[20968],"v":["0"]},{"x":"225","y":"224","t":[20974],"v":["0"]},{"x":"246","y":"53","t":[20988],"v":["0"]},{"x":"166","y":"45","t":[20988],"v":["0"]},{"x":"176","y":"135","t":[20988],"v":["0"]},{"x":"167","y":"193","t":[20989],"v":["2"]},{"x":"176","y":"193","t":[20989],"v":["1"]},{"x":"76","y":"68","t":[21000],"v":["0"]},{"x":"73","y":"138","t":[21056],"v":["0"]},{"x":"86","y":"140","t":[21056],"v":["0"]},{"x":"88","y":"149","t":[21056],"v":["0"]},{"x":"123","y":"145","t":[21056],"v":["0"]},{"x":"250","y":"197","t":[21089],"v":["2"]},{"x":"66","y":"74","t":[21089],"v":["0"]},{"x":"181","y":"182","t":[21091],"v":["1"]},{"x":"254","y":"225","t":[21091],"v":["0"]},{"x":"252","y":"231","t":[21091],"v":["0"]},{"x":"174","y":"70","t":[21296],"v":["0"]},{"x":"249","y":"63","t":[21327],"v":["5"]},{"x":"9","y":"140","t":[21331],"v":["0"]},{"x":"29","y":"128","t":[21331],"v":["1"]},{"x":"65","y":"142","t":[21331],"v":["1"]},{"x":"106","y":"81","t":[21331],"v":["1"]},{"x":"108","y":"96","t":[21331],"v":["0"]},{"x":"141","y":"160","t":[21331],"v":["0"]},{"x":"136","y":"176","t":[21331],"v":["1"]},{"x":"147","y":"246","t":[21332],"v":["1"]},{"x":"204","y":"233","t":[21332],"v":["1"]},{"x":"228","y":"225","t":[21332],"v":["2"]},{"x":"20","y":"253","t":[21337],"v":["1"]},{"x":"115","y":"249","t":[21337],"v":["0"]},{"x":"115","y":"253","t":[21337],"v":["1"]},{"x":"131","y":"248","t":[21337],"v":["1"]},{"x":"67","y":"217","t":[21338],"v":["0"]},{"x":"112","y":"243","t":[21338],"v":["1"]},{"x":"190","y":"226","t":[21338],"v":["1"]},{"x":"217","y":"184","t":[21338],"v":["1"]},{"x":"238","y":"183","t":[21338],"v":["1"]},{"x":"236","y":"162","t":[21338],"v":["0"]},{"x":"253","y":"142","t":[21341],"v":["1"]},{"x":"7","y":"10","t":[21344],"v":["2"]},{"x":"31","y":"7","t":[21344],"v":["2"]},{"x":"3","y":"128","t":[21344],"v":["0"]},{"x":"57","y":"10","t":[21344],"v":["0"]},{"x":"22","y":"148","t":[21344],"v":["0"]},{"x":"25","y":"159","t":[21344],"v":["0"]},{"x":"136","y":"45","t":[21348],"v":["0"]},{"x":"27","y":"230","t":[21353],"v":["0"]},{"x":"127","y":"8","t":[21382],"v":["0"]},{"x":"60","y":"142","t":[21382],"v":["1"]},{"x":"245","y":"122","t":[21382],"v":["0"]},{"x":"189","y":"156","t":[21390],"v":["1"]},{"x":"209","y":"162","t":[21390],"v":["0"]},{"x":"233","y":"171","t":[21390],"v":["0"]},{"x":"115","y":"58","t":[21403],"v":["0"]},{"x":"116","y":"62","t":[21403],"v":["0"]},{"x":"57","y":"252","t":[21629],"v":["0"]},{"x":"63","y":"225","t":[21629],"v":["0"]},{"x":"68","y":"208","t":[21629],"v":["0"]},{"x":"58","y":"1","t":[21675],"v":["0"]},{"x":"73","y":"200","t":[21705],"v":["0"]},{"x":"151","y":"175","t":[21705],"v":["0"]},{"x":"170","y":"84","t":[21719],"v":["0"]},{"x":"190","y":"72","t":[21719],"v":["0"]},{"x":"221","y":"72","t":[21719],"v":["0"]},{"x":"230","y":"71","t":[21719],"v":["0"]},{"x":"240","y":"76","t":[21719],"v":["0"]},{"x":"234","y":"79","t":[21719],"v":["0"]},{"x":"250","y":"80","t":[21719],"v":["1"]},{"x":"167","y":"216","t":[22068],"v":["0"]},{"x":"183","y":"111","t":[22071],"v":["0"]},{"x":"211","y":"114","t":[22071],"v":["0"]},{"x":"165","y":"214","t":[22081],"v":["0"]},{"x":"116","y":"44","t":[22085],"v":["0"]},{"x":"63","y":"76","t":[22085],"v":["0"]},{"x":"151","y":"46","t":[22085],"v":["0"]},{"x":"189","y":"10","t":[22109],"v":["0"]},{"x":"205","y":"22","t":[22109],"v":["0"]},{"x":"85","y":"43","t":[22115],"v":["1"]},{"x":"179","y":"209","t":[22116],"v":["1"]},{"x":"190","y":"208","t":[22116],"v":["1"]},{"x":"79","y":"229","t":[22358],"v":["1"]},{"x":"82","y":"238","t":[22358],"v":["0"]},{"x":"89","y":"221","t":[22358],"v":["0"]},{"x":"21","y":"155","t":[22358],"v":["0"]},{"x":"105","y":"246","t":[22358],"v":["0"]},{"x":"135","y":"207","t":[22358],"v":["2"]},{"x":"133","y":"217","t":[22358],"v":["0"]},{"x":"20","y":"91","t":[22376],"v":["2"]},{"x":"30","y":"87","t":[22376],"v":["3"]},{"x":"34","y":"85","t":[22376],"v":["2"]},{"x":"38","y":"82","t":[22376],"v":["0"]},{"x":"15","y":"77","t":[22376],"v":["1"]},{"x":"45","y":"67","t":[22376],"v":["3"]},{"x":"48","y":"59","t":[22376],"v":["0"]},{"x":"7","y":"56","t":[22376],"v":["1"]},{"x":"59","y":"62","t":[22376],"v":["2"]},{"x":"62","y":"60","t":[22376],"v":["1"]},{"x":"25","y":"51","t":[22376],"v":["0"]},{"x":"25","y":"52","t":[22376],"v":["0"]},{"x":"70","y":"41","t":[22376],"v":["4"]},{"x":"73","y":"46","t":[22376],"v":["1"]},{"x":"73","y":"43","t":[22376],"v":["2"]},{"x":"80","y":"41","t":[22376],"v":["1"]},{"x":"122","y":"17","t":[22376],"v":["1"]},{"x":"119","y":"15","t":[22448],"v":["1"]},{"x":"58","y":"135","t":[22454],"v":["1"]},{"x":"121","y":"78","t":[22469],"v":["0"]},{"x":"104","y":"250","t":[22747],"v":["2"]},{"x":"177","y":"230","t":[22747],"v":["1"]},{"x":"61","y":"8","t":[22754],"v":["0"]}]